cloud_backup/__init__.py
cloud_backup/config.py
cloud_backup/installing.py
cloud_backup/listing.py
cloud_backup/backup/__init__.py
cloud_backup/backup/backupfile.py
cloud_backup/backup/backupset.py
cloud_backup/backup/restorefile.py
cloud_backup/backup/compression/__init__.py
cloud_backup/backup/compression/compressfile.py
cloud_backup/backup/compression/uncompressfile.py
cloud_backup/backup/encryption/__init__.py
cloud_backup/backup/encryption/decryptedfile.py
cloud_backup/backup/encryption/encryptedfile.py
cloud_backup/cli/__init__.py
cloud_backup/cli/cli_library.py
cloud_backup/cli/main.py
cloud_backup/cli/optional_int_range.py
cloud_backup-1.0.0.dist-info/LICENSE
cloud_backup-1.0.0.dist-info/METADATA
cloud_backup-1.0.0.dist-info/WHEEL
cloud_backup-1.0.0.dist-info/entry_points.txt
cloud_backup-1.0.0.dist-info/top_level.txt
cloud_backup-1.0.0.dist-info/RECORD
